Workbook

Sheet Raw Data
A1: Order ID | B1: Date | C1: Region | D1: Category | E1: Product | F1: Sales Rep | G1: Customer Segment | H1: Payment Method | I1: Units Sold | J1: Unit Price | K1: Sales Amount | L1: Month
A2: ORD-100276 | B2: 45871 | C2: South | D2: Apparel | E2: Men's T-Shirt | F2: N. Iyer | G2: Retail | H2: UPI | I2: 10 | J2: 727 | K2: =I2*J2 -> 7270 | L2: =TEXT(B2,"MMM-YYYY") -> Aug-2025
A3: ORD-100242 | B3: 45872 | C3: South | D3: Furniture | E3: Office Chair | F3: A. Sharma | G3: Retail | H3: Credit Card | I3: 6 | J3: 4996 | K3: =I3*J3 -> 29976 | L3: =TEXT(B3,"MMM-YYYY") -> Aug-2025
A4: ORD-100397 | B4: 45874 | C4: East | D4: Apparel | E4: Denim Jacket | F4: S. Joshi | G4: Retail | H4: Cash on Delivery | I4: 9 | J4: 869 | K4: =I4*J4 -> 7821 | L4: =TEXT(B4,"MMM-YYYY") -> Aug-2025
A5: ORD-100141 | B5: 45875 | C5: North | D5: Apparel | E5: Running Shoes | F5: S. Joshi | G5: Wholesale | H5: Net Banking | I5: 10 | J5: 1142 | K5: =I5*J5 -> 11420 | L5: =TEXT(B5,"MMM-YYYY") -> Aug-2025
A6: ORD-100174 | B6: 45875 | C6: South | D6: Home Appliances | E6: Mixer Grinder | F6: A. Sharma | G6: Retail | H6: Credit Card | I6: 3 | J6: 3243 | K6: =I6*J6 -> 9729 | L6: =TEXT(B6,"MMM-YYYY") -> Aug-2025
A7: ORD-100207 | B7: 45875 | C7: North | D7: Furniture | E7: Office Chair | F7: K. Reddy | G7: Retail | H7: Credit Card | I7: 8 | J7: 4639 | K7: =I7*J7 -> 37112 | L7: =TEXT(B7,"MMM-YYYY") -> Aug-2025
A8: ORD-100239 | B8: 45875 | C8: North | D8: Apparel | E8: Denim Jacket | F8: M. Khan | G8: Online | H8: Cash on Delivery | I8: 6 | J8: 847 | K8: =I8*J8 -> 5082 | L8: =TEXT(B8,"MMM-YYYY") -> Aug-2025
A9: ORD-100353 | B9: 45877 | C9: East | D9: Furniture | E9: Bookshelf | F9: N. Iyer | G9: Retail | H9: UPI | I9: 11 | J9: 4381 | K9: =I9*J9 -> 48191 | L9: =TEXT(B9,"MMM-YYYY") -> Aug-2025
A10: ORD-100030 | B10: 45880 | C10: North | D10: Furniture | E10: Office Chair | F10: S. Joshi | G10: Online | H10: Credit Card | I10: 7 | J10: 5432 | K10: =I10*J10 -> 38024 | L10: =TEXT(B10,"MMM-YYYY") -> Aug-2025
A11: ORD-100220 | B11: 45880 | C11: North | D11: Electronics | E11: Power Bank | F11: S. Joshi | G11: Wholesale | H11: Cash on Delivery | I11: 5 | J11: 2229 | K11: =I11*J11 -> 11145 | L11: =TEXT(B11,"MMM-YYYY") -> Aug-2025
A12: ORD-100281 | B12: 45880 | C12: North | D12: Furniture | E12: Office Chair | F12: K. Reddy | G12: Retail | H12: Credit Card | I12: 4 | J12: 3828 | K12: =I12*J12 -> 15312 | L12: =TEXT(B12,"MMM-YYYY") -> Aug-2025
A13: ORD-100022 | B13: 45883 | C13: East | D13: Electronics | E13: Wireless Earbuds | F13: M. Khan | G13: Online | H13: Cash on Delivery | I13: 3 | J13: 2151 | K13: =I13*J13 -> 6453 | L13: =TEXT(B13,"MMM-YYYY") -> Aug-2025
... A401: ORD-100284 | B401: 46234 | C401: South | D401: Apparel | E401: Women's Kurti | F401: A. Sharma | G401: Retail | H401: Cash on Delivery | I401: 7 | J401: 804 | K401: =I401*J401 -> 5628 | L401: =TEXT(B401,"MMM-YYYY") -> Jul-2026

Sheet Dashboard
A1: Sales Performance Dashboard
A2: Sample dataset (Aug 2025 - Jul 2026) — replace Raw Data sheet with real records
A4: Filter by Region: | B4: All
A6: Total Sales (Rs.) | B6: Total Orders | C6: Total Units Sold | D6: Avg Order Value (Rs.) | E6: Top Category (by Sales)
A7: =SUMIFS('Raw Data'!$K$2:$K$401,'Raw Data'!$C$2:$C$401,IF($B$4="All","<>",$B$4)) -> 6104802 | B7: =COUNTIFS('Raw Data'!$C$2:$C$401,IF($B$4="All","<>",$B$4)) -> 400 | C7: =SUMIFS('Raw Data'!$I$2:$I$401,'Raw Data'!$C$2:$C$401,IF($B$4="All","<>",$B$4)) -> 2535 | D7: =IFERROR(A7/B7,0) -> 15262.005 | E7: =INDEX(A11:A14,MATCH(MAX(B11:B14),B11:B14,0)) -> Electronics
A10: Category | B10: Sales (Rs.) | D10: Month | E10: Sales (Rs.)
A11: Electronics | B11: =SUMIFS('Raw Data'!$K$2:$K$401,'Raw Data'!$C$2:$C$401,IF($B$4="All","<>",$B$4),'Raw Data'!$D$2:$D$401,A11) -> 2079436 | D11: Aug-2025 | E11: =SUMIFS('Raw Data'!$K$2:$K$401,'Raw Data'!$C$2:$C$401,IF($B$4="All","<>",$B$4),'Raw Data'!$L$2:$L$401,D11) -> 484985
A12: Home Appliances | B12: =SUMIFS('Raw Data'!$K$2:$K$401,'Raw Data'!$C$2:$C$401,IF($B$4="All","<>",$B$4),'Raw Data'!$D$2:$D$401,A12) -> 2040062 | D12: Sep-2025 | E12: =SUMIFS('Raw Data'!$K$2:$K$401,'Raw Data'!$C$2:$C$401,IF($B$4="All","<>",$B$4),'Raw Data'!$L$2:$L$401,D12) -> 408369
A13: Apparel | B13: =SUMIFS('Raw Data'!$K$2:$K$401,'Raw Data'!$C$2:$C$401,IF($B$4="All","<>",$B$4),'Raw Data'!$D$2:$D$401,A13) -> 568509 | D13: Oct-2025 | E13: =SUMIFS('Raw Data'!$K$2:$K$401,'Raw Data'!$C$2:$C$401,IF($B$4="All","<>",$B$4),'Raw Data'!$L$2:$L$401,D13) -> 502333
A14: Furniture | B14: =SUMIFS('Raw Data'!$K$2:$K$401,'Raw Data'!$C$2:$C$401,IF($B$4="All","<>",$B$4),'Raw Data'!$D$2:$D$401,A14) -> 1416795 | D14: Nov-2025 | E14: =SUMIFS('Raw Data'!$K$2:$K$401,'Raw Data'!$C$2:$C$401,IF($B$4="All","<>",$B$4),'Raw Data'!$L$2:$L$401,D14) -> 557482
D15: Dec-2025 | E15: =SUMIFS('Raw Data'!$K$2:$K$401,'Raw Data'!$C$2:$C$401,IF($B$4="All","<>",$B$4),'Raw Data'!$L$2:$L$401,D15) -> 680453
D16: Jan-2026 | E16: =SUMIFS('Raw Data'!$K$2:$K$401,'Raw Data'!$C$2:$C$401,IF($B$4="All","<>",$B$4),'Raw Data'!$L$2:$L$401,D16) -> 454013
A17: Sales Rep Performance | D17: Customer Segment Split
A18: Sales Rep | B18: Sales (Rs.) | D18: Segment | E18: Sales (Rs.)
A19: A. Sharma | B19: =SUMIFS('Raw Data'!$K$2:$K$401,'Raw Data'!$C$2:$C$401,IF($B$4="All","<>",$B$4),'Raw Data'!$F$2:$F$401,A19) -> 1043383 | D19: Retail | E19: =SUMIFS('Raw Data'!$K$2:$K$401,'Raw Data'!$C$2:$C$401,IF($B$4="All","<>",$B$4),'Raw Data'!$G$2:$G$401,D19) -> 2921926
A20: P. Verma | B20: =SUMIFS('Raw Data'!$K$2:$K$401,'Raw Data'!$C$2:$C$401,IF($B$4="All","<>",$B$4),'Raw Data'!$F$2:$F$401,A20) -> 1176086 | D20: Wholesale | E20: =SUMIFS('Raw Data'!$K$2:$K$401,'Raw Data'!$C$2:$C$401,IF($B$4="All","<>",$B$4),'Raw Data'!$G$2:$G$401,D20) -> 1261465
A21: N. Iyer | B21: =SUMIFS('Raw Data'!$K$2:$K$401,'Raw Data'!$C$2:$C$401,IF($B$4="All","<>",$B$4),'Raw Data'!$F$2:$F$401,A21) -> 819065 | D21: Online | E21: =SUMIFS('Raw Data'!$K$2:$K$401,'Raw Data'!$C$2:$C$401,IF($B$4="All","<>",$B$4),'Raw Data'!$G$2:$G$401,D21) -> 1921411
A22: K. Reddy | B22: =SUMIFS('Raw Data'!$K$2:$K$401,'Raw Data'!$C$2:$C$401,IF($B$4="All","<>",$B$4),'Raw Data'!$F$2:$F$401,A22) -> 898620 | D22: Jul-2026 | E22: =SUMIFS('Raw Data'!$K$2:$K$401,'Raw Data'!$C$2:$C$401,IF($B$4="All","<>",$B$4),'Raw Data'!$L$2:$L$401,D22) -> 635619
A23: S. Joshi | B23: =SUMIFS('Raw Data'!$K$2:$K$401,'Raw Data'!$C$2:$C$401,IF($B$4="All","<>",$B$4),'Raw Data'!$F$2:$F$401,A23) -> 1073662
A24: M. Khan | B24: =SUMIFS('Raw Data'!$K$2:$K$401,'Raw Data'!$C$2:$C$401,IF($B$4="All","<>",$B$4),'Raw Data'!$F$2:$F$401,A24) -> 1093986
